rmrl/.gitignore
rmrl/__init__.py
rmrl/__main__.py
rmrl/constants.py
rmrl/document.py
rmrl/lines.py
rmrl/load_templates.py
rmrl/pens/__init__.py
rmrl/pens/ballpoint.py
rmrl/pens/calligraphy.py
rmrl/pens/eraser.py
rmrl/pens/fineliner.py
rmrl/pens/generic.py
rmrl/pens/highlighter.py
rmrl/pens/marker.py
rmrl/pens/mechanicalpencil.py
rmrl/pens/paintbrush.py
rmrl/pens/paintbrush_textures_log/0.00.ppm
rmrl/pens/paintbrush_textures_log/0.01.ppm
rmrl/pens/paintbrush_textures_log/0.02.ppm
rmrl/pens/paintbrush_textures_log/0.03.ppm
rmrl/pens/paintbrush_textures_log/0.04.ppm
rmrl/pens/paintbrush_textures_log/0.05.ppm
rmrl/pens/paintbrush_textures_log/0.06.ppm
rmrl/pens/paintbrush_textures_log/0.07.ppm
rmrl/pens/paintbrush_textures_log/0.08.ppm
rmrl/pens/paintbrush_textures_log/0.09.ppm
rmrl/pens/paintbrush_textures_log/0.10.ppm
rmrl/pens/paintbrush_textures_log/0.11.ppm
rmrl/pens/paintbrush_textures_log/0.12.ppm
rmrl/pens/paintbrush_textures_log/0.13.ppm
rmrl/pens/paintbrush_textures_log/0.14.ppm
rmrl/pens/paintbrush_textures_log/0.15.ppm
rmrl/pens/paintbrush_textures_log/0.16.ppm
rmrl/pens/paintbrush_textures_log/0.17.ppm
rmrl/pens/paintbrush_textures_log/0.18.ppm
rmrl/pens/paintbrush_textures_log/0.19.ppm
rmrl/pens/paintbrush_textures_log/0.20.ppm
rmrl/pens/paintbrush_textures_log/0.21.ppm
rmrl/pens/paintbrush_textures_log/0.22.ppm
rmrl/pens/paintbrush_textures_log/0.23.ppm
rmrl/pens/paintbrush_textures_log/0.24.ppm
rmrl/pens/paintbrush_textures_log/0.25.ppm
rmrl/pens/paintbrush_textures_log/0.26.ppm
rmrl/pens/paintbrush_textures_log/0.27.ppm
rmrl/pens/paintbrush_textures_log/0.28.ppm
rmrl/pens/paintbrush_textures_log/0.29.ppm
rmrl/pens/paintbrush_textures_log/0.30.ppm
rmrl/pens/paintbrush_textures_log/0.31.ppm
rmrl/pens/paintbrush_textures_log/0.32.ppm
rmrl/pens/paintbrush_textures_log/0.33.ppm
rmrl/pens/paintbrush_textures_log/0.34.ppm
rmrl/pens/paintbrush_textures_log/0.35.ppm
rmrl/pens/paintbrush_textures_log/0.36.ppm
rmrl/pens/paintbrush_textures_log/0.37.ppm
rmrl-0.2.1.dist-info/COPYING
rmrl-0.2.1.dist-info/WHEEL
rmrl-0.2.1.dist-info/METADATA
rmrl-0.2.1.dist-info/RECORD
