Metadata-Version: 2.1
Name: rmrl
Version: 0.2.1
Summary: Render reMarkable documents to PDF
Home-page: https://github.com/rschroll/rmrl
License: GPLv3
Author: Robert Schroll
Author-email: rschroll@gmail.com
Requires-Python: >=3.7,<4.0
Classifier: License :: Other/Proprietary License
Classifier: Programming Language :: Python :: 3
Classifier: Programming Language :: Python :: 3.7
Classifier: Programming Language :: Python :: 3.8
Classifier: Programming Language :: Python :: 3.9
Requires-Dist: pdfrw (>=0.4,<0.5)
Requires-Dist: reportlab (>=3.5.59,<4.0.0)
Requires-Dist: svglib (>=1.0.1,<2.0.0)
Requires-Dist: xdg (>=5.0.1,<6.0.0)
Project-URL: Repository, https://github.com/rschroll/rmrl
